dbe_cli/__init__.py
dbe_cli/__main__.py
dbe_cli/base_type.py
dbe_cli/conf.py
dbe_cli/core.py
dbe_cli/db_op.py
dbe_cli/exceptions.py
dbe_cli/main.py
dbe_cli/tfs_cache.py
dbe_cli/utils.py
dbe_cli-0.3.0.dist-info/LICENSE
dbe_cli-0.3.0.dist-info/METADATA
dbe_cli-0.3.0.dist-info/WHEEL
dbe_cli-0.3.0.dist-info/top_level.txt
dbe_cli-0.3.0.dist-info/RECORD
