Metadata-Version: 2.1
Name: dbe-cli
Version: 0.3.0
Summary: Better performance, higher efficiency and more features.
Author-email: Claude Manchester <atlanmatrix@gmail.com>
License: GNU GENERAL PUBLIC LICENSE
Project-URL: Homepage, https://github.com/atlanmatrix/DBExplorer_CLI
Project-URL: Bug Tracker, https://github.com/atlanmatrix/DBExplorer_CLI/issues
Classifier: Programming Language :: Python :: 3
Classifier: License :: OSI Approved :: MIT License
Classifier: Operating System :: OS Independent
Requires-Python: >=3.7
License-File: LICENSE
Requires-Dist: requests (>=2.28.1)
